{
  "reorganization_timestamp": "2025-05-27T12:04:39.121012",
  "status": "completed",
  "structure_changes": {
    "old_main_files": [
      "./main.py",
      "src/main.py"
    ],
    "new_structure": "autocura/",
    "backup_location": "backup_reorganization",
    "migration_summary": {
      "core_modules": "autocura/core/",
      "services": "autocura/services/",
      "monitoring": "autocura/monitoring/",
      "security": "autocura/security/",
      "evolution": "autocura/evolution/",
      "api": "autocura/api/",
      "utils": "autocura/utils/"
    }
  },
  "docker_updates": {
    "new_dockerfile": "deployment/docker/Dockerfile.modular",
    "new_compose": "deployment/docker/docker-compose.modular.yml",
    "services": [
      "autocura-api",
      "redis",
      "postgres",
      "prometheus",
      "grafana"
    ]
  },
  "next_steps": [
    "1. Verificar migração dos arquivos",
    "2. Atualizar importações nos testes",
    "3. Testar nova estrutura Docker",
    "4. Executar testes de integração",
    "5. Atualizar documentação"
  ],
  "compatibility": {
    "fallback_enabled": true,
    "old_structure_preserved": true,
    "gradual_migration": true
  }
}